flask_ngrok_st.py
flask_ngrok_st-1.0.3.dist-info/LICENSE
flask_ngrok_st-1.0.3.dist-info/METADATA
flask_ngrok_st-1.0.3.dist-info/WHEEL
flask_ngrok_st-1.0.3.dist-info/top_level.txt
flask_ngrok_st-1.0.3.dist-info/RECORD
