Metadata-Version: 2.1
Name: flask-ngrok-st
Version: 1.0.3
Summary: A simple way to demo Flask apps from your machine.
Home-page: https://github.com/jakbin/flask-ngrok-st
Author: Jak Bin
License: UNKNOWN
Keywords: flask ngrok demo
Platform: UNKNOWN
Classifier: Programming Language :: Python :: 3.6
Classifier: License :: OSI Approved :: Apache Software License
Classifier: Operating System :: OS Independent
Requires-Dist: Flask (>=0.14.0)
Requires-Dist: requests
